pystubber/__init__.py
pystubber/cli.py
pystubber/stubber.py
pystubber-0.1.2.dist-info/entry_points.txt
pystubber-0.1.2.dist-info/LICENSE
pystubber-0.1.2.dist-info/WHEEL
pystubber-0.1.2.dist-info/METADATA
pystubber-0.1.2.dist-info/RECORD
