Metadata-Version: 2.1
Name: pystubber
Version: 0.1.2
Summary: pystubber - Creates a stub python file from a python module
Home-page: https://github.com/alanjds/pystubber
License: UNKNOWN
Author: Alan Justino da Silva
Author-email: alan.justino@yahoo.com.br
Requires-Python: ~=3.5
Classifier: Development Status :: 2 - Pre-Alpha
Classifier: Intended Audience :: Developers
Classifier: License :: OSI Approved :: Apache Software License
Classifier: Natural Language :: English
Classifier: Programming Language :: Python :: 3
Classifier: Programming Language :: Python :: 3.6
